spyndle_web_api/__init__.py
spyndle_web_api/client/Client.py
spyndle_web_api/client/__init__.py
spyndle_web_api/models/IntervalList.py
spyndle_web_api/models/LabMember.py
spyndle_web_api/models/NumpyArray.py
spyndle_web_api/models/Session.py
spyndle_web_api/models/Subject.py
spyndle_web_api/server/__init__.py
spyndle_web_api/server/main.py
spyndle_web_api-0.1.0.dist-info/METADATA
spyndle_web_api-0.1.0.dist-info/WHEEL
spyndle_web_api-0.1.0.dist-info/RECORD
