Metadata-Version: 2.1
Name: spyndle-web-api
Version: 0.1.0
Summary: A non-destructive Web API for Spyglass
Author: Jeremy Magland
Requires-Python: >=3.9,<4.0
Classifier: Programming Language :: Python :: 3
Classifier: Programming Language :: Python :: 3.9
Classifier: Programming Language :: Python :: 3.10
Classifier: Programming Language :: Python :: 3.11
Classifier: Programming Language :: Python :: 3.12
Requires-Dist: fastapi (>=0.109.0,<0.110.0)
Requires-Dist: uvicorn (>=0.27.0,<0.28.0)
